pygptcli/__init__.py
pygptcli/__main__.py
pygptcli/main.py
pygptcli-0.1.3.dist-info/LICENSE
pygptcli-0.1.3.dist-info/METADATA
pygptcli-0.1.3.dist-info/WHEEL
pygptcli-0.1.3.dist-info/RECORD
